microcore/__init__.py
microcore/_env.py
microcore/_llm_functions.py
microcore/_prepare_llm_args.py
microcore/ai_modules.py
microcore/configuration.py
microcore/file_cache.py
microcore/file_storage.py
microcore/images.py
microcore/interactive_setup.py
microcore/json_parsing.py
microcore/llm_backends.py
microcore/lm_client.py
microcore/logging.py
microcore/mcp.py
microcore/message_types.py
microcore/metrics.py
microcore/presets.py
microcore/python.py
microcore/tokenizing.py
microcore/types.py
microcore/ui.py
microcore/utils.py
microcore/ai_func/__init__.py
microcore/ai_func/ai-func.json.j2
microcore/ai_func/ai-func.pythonic.j2
microcore/ai_func/ai-func.tag.j2
microcore/embedding_db/__init__.py
microcore/embedding_db/chromadb.py
microcore/embedding_db/qdrant.py
microcore/llm/__init__.py
microcore/llm/anthropic.py
microcore/llm/google_genai.py
microcore/llm/local_llm.py
microcore/llm/local_transformers.py
microcore/llm/openai.py
microcore/llm/shared.py
microcore/templating/__init__.py
microcore/templating/jinja2.py
microcore/text2speech/elevenlabs.py
microcore/wrappers/__init__.py
microcore/wrappers/llm_response_wrapper.py
microcore/wrappers/prompt_wrapper.py
ai_microcore-5.0.1.dist-info/licenses/LICENSE
ai_microcore-5.0.1.dist-info/WHEEL
ai_microcore-5.0.1.dist-info/METADATA
ai_microcore-5.0.1.dist-info/RECORD
