Metadata-Version: 2.4
Name: ai-microcore
Version: 5.0.1
Summary: # Minimalistic Foundation for AI Applications
Keywords: llm,large language models,ai,similarity search,ai search,gpt,openai,framework,adapter,anthropic,google gemini,google vertex ai
Author-email: Vitalii Stepanenko <mail@vitaliy.in>
Maintainer-email: Vitalii Stepanenko <mail@vitaliy.in>
Requires-Python: >=3.10
Classifier: Programming Language :: Python :: 3
Classifier: Programming Language :: Python :: 3.10
Classifier: Programming Language :: Python :: 3.11
Classifier: Programming Language :: Python :: 3.12
Classifier: Programming Language :: Python :: 3.13
Classifier: License :: OSI Approved :: MIT License
Classifier: Operating System :: OS Independent
Classifier: Intended Audience :: Developers
Classifier: Topic :: Software Development :: Libraries :: Application Frameworks
Classifier: Topic :: Scientific/Engineering :: Artificial Intelligence
Classifier: Development Status :: 5 - Production/Stable
License-File: LICENSE
Requires-Dist: openai>=0.28.1,<2
Requires-Dist: python-dotenv~=1.1.0
Requires-Dist: Jinja2~=3.1.2
Requires-Dist: colorama~=0.4.6
Requires-Dist: PyYAML~=6.0
Requires-Dist: chardet~=5.2.0
Requires-Dist: tiktoken>=0.7.0,<1.0
Requires-Dist: mcp>=1.10.1,<2.0
Requires-Dist: fastmcp>=2.10.2,<3.0
Requires-Dist: docstring_parser~=0.16.0
Requires-Dist: httpx~=0.28.1
Project-URL: Bug Tracker, https://github.com/Nayjest/ai-microcore/issues
Project-URL: Source Code, https://github.com/Nayjest/ai-microcore
